wagtail_dsfr/__init__.py
wagtail_dsfr/apps.py
wagtail_dsfr/manage.py
wagtail_dsfr/blog/__init__.py
wagtail_dsfr/blog/admin.py
wagtail_dsfr/blog/apps.py
wagtail_dsfr/blog/blocks.py
wagtail_dsfr/blog/managers.py
wagtail_dsfr/blog/models.py
wagtail_dsfr/blog/utils.py
wagtail_dsfr/blog/views.py
wagtail_dsfr/blog/migrations/0001_initial.py
wagtail_dsfr/blog/migrations/0001_squashed_0048_blogentrypage_preview_image_and_more.py
wagtail_dsfr/blog/migrations/0002_alter_blogentrypage_body_alter_blogindexpage_body.py
wagtail_dsfr/blog/migrations/0003_blogentrypage_header_color_class_and_more.py
wagtail_dsfr/blog/migrations/0004_alter_blogentrypage_body_alter_blogindexpage_body.py
wagtail_dsfr/blog/migrations/0005_delete_tag_blogentrypage_header_cta_text_and_more.py
wagtail_dsfr/blog/migrations/0006_category_colophon_alter_blogentrypage_body_and_more.py
wagtail_dsfr/blog/migrations/0007_alter_blogentrypage_body_and_more.py
wagtail_dsfr/blog/migrations/0008_alter_blogentrypage_body_alter_blogindexpage_body_and_more.py
wagtail_dsfr/blog/migrations/0009_alter_blogentrypage_body_alter_blogindexpage_body_and_more.py
wagtail_dsfr/blog/migrations/0010_alter_blogentrypage_body_alter_blogindexpage_body_and_more.py
wagtail_dsfr/blog/migrations/0011_alter_blogentrypage_body_alter_blogindexpage_body_and_more.py
wagtail_dsfr/blog/migrations/0012_alter_blogentrypage_body_alter_blogindexpage_body_and_more.py
wagtail_dsfr/blog/migrations/0013_alter_blogentrypage_body_alter_blogindexpage_body_and_more.py
wagtail_dsfr/blog/migrations/0014_alter_blogentrypage_body_alter_blogindexpage_body_and_more.py
wagtail_dsfr/blog/migrations/0015_alter_blogentrypage_body_alter_blogindexpage_body.py
wagtail_dsfr/blog/migrations/0016_alter_blogentrypage_body_alter_blogindexpage_body.py
wagtail_dsfr/blog/migrations/0017_alter_blogentrypage_body_alter_blogindexpage_body_and_more.py
wagtail_dsfr/blog/migrations/0018_alter_blogentrypage_body_alter_blogindexpage_body_and_more.py
wagtail_dsfr-2.4.0rc2.dist-info/METADATA
wagtail_dsfr-2.4.0rc2.dist-info/WHEEL
wagtail_dsfr-2.4.0rc2.dist-info/top_level.txt
wagtail_dsfr-2.4.0rc2.dist-info/RECORD
