Metadata-Version: 2.4
Name: wagtail-dsfr
Version: 2.4.0rc2
Summary: Gestionnaire de contenu permettant de créer et gérer un site internet basé sur le Système de design de l'État, accessible et responsive
Author-email: Sébastien Reuiller <sebastien.reuiller@beta.gouv.fr>, Sylvain Boissel <sylvain.boissel@beta.gouv.fr>, Lucien Mollard <lucien.mollard@beta.gouv.fr>, Lucie Laporte <lucie.laporte@beta.gouv.fr>
Maintainer-email: Sylvain Boissel <sylvain.boissel@beta.gouv.fr>, Lucien Mollard <lucien.mollard@beta.gouv.fr>, Lucie Laporte <lucie.laporte@beta.gouv.fr>
Requires-Python: <4.0,>=3.11
Requires-Dist: django-dsfr>=2.4.0
Requires-Dist: django>=5.2.3
Requires-Dist: wagtail>=7.0.1
Requires-Dist: psycopg2-binary>=2.9.10
Requires-Dist: python-dotenv>=1.1.0
Requires-Dist: dj-database-url>=3.0.0
Requires-Dist: gunicorn>=23.0.0
Requires-Dist: dj-static>=0.0.6
Requires-Dist: wagtailmenus>=4.0.3
Requires-Dist: wagtail-modeladmin>=2.2.0
Requires-Dist: wagtail-markdown>=0.12.1
Requires-Dist: unidecode>=1.4.0
Requires-Dist: beautifulsoup4>=4.13.4
Requires-Dist: django-taggit>=6.1.0
Requires-Dist: wagtail-localize>=1.12.1
Requires-Dist: icalendar>=6.3.1
Requires-Dist: faker>=37.4.0
Requires-Dist: rust-just>=1.40.0
Requires-Dist: mozilla-django-oidc>=4.0.1
Requires-Dist: pyyaml>=6.0.2
